dockercor/__init__.py
dockercor/cli.py
dockercor/docker_manager.py
dockercor-0.1.3.dist-info/LICENSE
dockercor-0.1.3.dist-info/METADATA
dockercor-0.1.3.dist-info/WHEEL
dockercor-0.1.3.dist-info/entry_points.txt
dockercor-0.1.3.dist-info/RECORD
