Metadata-Version: 2.1
Name: dockercor
Version: 0.1.3
Summary: A lightweight Python package for managing Docker images and running containers with ease.
Home-page: https://github.com/infocornouaille/dockercor.git
License: MIT
Author: infocornouaille
Author-email: 90894019+infocornouaille@users.noreply.github.com
Requires-Python: >=3.11,<4.0
Classifier: License :: OSI Approved :: MIT License
Classifier: Programming Language :: Python :: 3
Classifier: Programming Language :: Python :: 3.11
Classifier: Programming Language :: Python :: 3.12
Requires-Dist: docker (>=7.1.0,<8.0.0)
Requires-Dist: typer (>=0.12.5,<0.13.0)
Project-URL: Repository, https://github.com/infocornouaille/dockercor.git
